Metadata-Version: 2.4
Name: agent-framework-mistralai
Version: 0.0.0a1
Summary: Microsoft Agent Framework MistralAI.
Author-email: Microsoft <af-support@microsoft.com>
Requires-Python: >=3.10
License-File: LICENSE
